{
	"default_object" : "cockroach",
	"coal_object": "coal",
	"final_object":  "gold",
	"timer_values" : [1, 3, 5],
	"speed_of_hanger" : 0.007,
	"objects": [
	{
		"name": "coal",
		"saturation": -0.3,
		"model": "assets/models/coal",
		"box": "0.653;0.591;0.681",
		"scale": "1;1;1",
		"rotation": "0;0;0",
		"origin_offset": "-0.035;-0.011;-0.044",
		"card": "assets/textures/cards/coal.png",
		"sound_drop": "assets/sounds/coal_drop.mp3",
		"sound_eat": "assets/sounds/coal_eat.mp3",
		"sound_pickup": "assets/sounds/coal_pickup.mp3"
	},
	{
		"name": "can",
		"saturation": -0.05,
		"model": "assets/models/can",
		"box": "1;1;1",
		"scale": "1;1;1",
		"rotation": "0;0;0",
		"origin_offset": "0.0;-0.5;0.0",
		"card": "assets/textures/cards/can.png",
		"sound_drop": "assets/sounds/can_drop.mp3",
		"sound_eat": "assets/sounds/can_eat.mp3",
		"sound_pickup": "assets/sounds/can_pickup.mp3"
	},
	{
		"name": "fish",
		"saturation": 0.2,
		"model": "assets/models/fish",
		"box": "1.269;0.139;1.251",
		"scale": "1;1;1",
		"rotation": "0;0;0",
		"origin_offset": "0.137;0.000;-0.073",
		"card": "assets/textures/cards/fish.png",
		"sound_drop": "assets/sounds/fish_drop.mp3",
		"sound_eat": "assets/sounds/fish_eat.mp3",
		"sound_pickup": "assets/sounds/fish_pickup.mp3"
	},
	{
		"name": "finger",
		"saturation": 0.4,
		"model": "assets/models/finger",
		"box": "0.661;0.204;0.255",
		"scale": "1;1;1",
		"rotation": "0;0;0",
		"origin_offset": "-0.001;0.000;0.000",
		"card": "assets/textures/cards/finger.png",
		"sound_drop": "assets/sounds/finger_drop.mp3",
		"sound_eat": "assets/sounds/finger_eat.mp3",
		"sound_pickup": "assets/sounds/finger_pickup.mp3"
	},
	{
		"name": "glass",
		"saturation": 0.5,
		"model": "assets/models/glass",
		"box": "0.446;0.670;0.515",
		"scale": "1;1;1",
		"rotation": "0;0;0",
		"origin_offset": "0.000;-0.1;0.000",
		"card": "assets/textures/cards/glass.png",
		"sound_drop": "assets/sounds/glass_drop.mp3",
		"sound_eat": "assets/sounds/glass_eat.mp3",
		"sound_pickup": "assets/sounds/glass_pickup.mp3"
	},
	{
		"name": "rat",
		"saturation": 0.4,
		"model": "assets/models/rat",
		"box": "1;1;1",
		"scale": "1;1;1",
		"rotation": "0;0;0",
		"origin_offset": "0.0;-0.25;0.0",
		"card": "assets/textures/cards/rat.png",
		"sound_drop": "assets/sounds/rat_drop.mp3",
		"sound_eat": "assets/sounds/rat_eat.mp3",
		"sound_pickup": "assets/sounds/rat_pickup.mp3"
	},
	{
		"name": "ketchup",
		"saturation": 0.15,
		"model": "assets/models/ketchup",
		"box": "0.542;1.079;0.288",
		"scale": "1;1;1",
		"rotation": "0;0;0",
		"origin_offset": "0.000;-0.089;0.000",
		"card": "assets/textures/cards/ketchup.png",
		"sound_drop": "assets/sounds/ketchup_drop.mp3",
		"sound_eat": "assets/sounds/ketchup_eat.mp3",
		"sound_pickup": "assets/sounds/ketchup_pickup.mp3"
	},
	{
		"name": "blade",
		"saturation": 0.2,
		"model": "assets/models/blade",
		"box": "0.950;0.054;1.232",
		"scale": "1;1;1",
		"rotation": "0;0;0",
		"origin_offset": "0.000;0.000;0.000",
		"card": "assets/textures/cards/blade.png",
		"sound_drop": "assets/sounds/blade_drop.mp3",
		"sound_eat": "assets/sounds/blade_eat.mp3",
		"sound_pickup": "assets/sounds/blade_pickup.mp3"
	},
	{
		"name": "brain",
		"saturation": 0.4,
		"model": "assets/models/brain",
		"box": "2.389;1.044;2.418",
		"scale": "0.4;0.4;0.4",
		"rotation": "0;0;0",
		"origin_offset": "0.112;-0.243;0.107",
		"card": "assets/textures/cards/brain.png",
		"sound_drop": "assets/sounds/brain_drop.mp3",
		"sound_eat": "assets/sounds/brain_eat.mp3",
		"sound_pickup": "assets/sounds/brain_pickup.mp3",
		"originoffset": "0.112;-0.193;0.107",
	},
	{
		"name": "skull",
		"saturation": 0.35,
		"model": "assets/models/skull",
		"box": "0.591;0.443;0.902",
		"scale": "1;1;1",
		"rotation": "0;0;0",
		"origin_offset": "-0.044;0.034;-0.004",
		"card": "assets/textures/cards/skull.png",
		"sound_drop": "assets/sounds/skull_drop.mp3",
		"sound_eat": "assets/sounds/skull_eat.mp3",
		"sound_pickup": "assets/sounds/skull_pickup.mp3",
		"originoffset": "-0.044;-0.044;-0.004",
	},
	{
		"name": "mask",
		"saturation": 1.0,
		"model": "assets/models/mask",
		"box": "1.143;1.037;1.886",
		"scale": "1;1;1",
		"rotation": "0;0;0",
		"origin_offset": "0.000;-0.29;0.126",
		"card": "assets/textures/cards/mask.png",
		"sound_drop": "assets/sounds/mask_drop.mp3",
		"sound_eat": "assets/sounds/mask_eat.mp3",
		"sound_pickup": "assets/sounds/mask_pickup.mp3",
		"originoffset": "0.000;0.329;0.126",
	},
	{
		"name": "tooth",
		"saturation": 0.2,
		"model": "assets/models/tooth",
		"box": "0.704;0.704;0.820",
		"scale": "1;1;1",
		"rotation": "0;0;0",
		"origin_offset": "0.008;0.042;0.008",
		"card": "assets/textures/cards/tooth.png",
		"sound_drop": "assets/sounds/tooth_drop.mp3",
		"sound_eat": "assets/sounds/tooth_eat.mp3",
		"sound_pickup": "assets/sounds/tooth_pickup.mp3",
		"originoffset": "0.008;-0.042;0.008",
	},
	{
		"name": "seeds",
		"saturation": 0.06,
		"model": "assets/models/seeds",
		"box": "1.052;0.300;1.088",
		"scale": "1;1;1",
		"rotation": "0;0;0",
		"origin_offset": "0.020;0.017;0.029",
		"card": "assets/textures/cards/seeds.png",
		"sound_drop": "assets/sounds/seeds_drop.mp3",
		"sound_eat": "assets/sounds/seeds_eat.mp3",
		"sound_pickup": "assets/sounds/seeds_pickup.mp3",
		"originoffset": "0.020;-0.017;0.029",
	},
	{
		"name": "apple",
		"saturation": 0.0,
		"model": "assets/models/apple",
		"box": "0.652;0.649;0.626",
		"scale": "1;1;1",
		"rotation": "0;0;0",
		"origin_offset": "0.012;-0.033;-0.018",
		"card": "assets/textures/cards/apple.png",
		"sound_drop": "assets/sounds/apple_drop.mp3",
		"sound_eat": "assets/sounds/apple_eat.mp3",
		"sound_pickup": "assets/sounds/apple_pickup.mp3",
		"originoffset": "0.012;-0.033;-0.018",
	},
	{
		"name": "nudlez",
		"saturation": 0.07,
		"model": "assets/models/nudlez",
		"box": "0.860;0.362;0.860",
		"scale": "1;1;1",
		"rotation": "0;0;0",
		"origin_offset": "0.000;0.025;0.000",
		"card": "assets/textures/cards/nudlez.png",
		"sound_drop": "assets/sounds/noodles_drop.mp3",
		"sound_eat": "assets/sounds/noodles_eat.mp3",
		"sound_pickup": "assets/sounds/noodles_pickup.mp3",
		"originoffset": "0.000;-0.025;0.000",
	},
	{
		"name": "sausages",
		"saturation": 0.07,
		"model": "assets/models/sausages",
		"box": "1.212;0.165;1.015",
		"scale": "1;1;1",
		"rotation": "0;0;0",
		"origin_offset": "-0.005;-0.073;0.001",
		"card": "assets/textures/cards/sausages.png",
		"sound_drop": "assets/sounds/sausages_drop.mp3",
		"sound_eat": "assets/sounds/sausages_eat.mp3",
		"sound_pickup": "assets/sounds/sausages_pickup.mp3",
		"originoffset": "-0.005;0.073;0.001",
	},
	{
		"name": "worms",
		"saturation": 0.01,
		"model": "assets/models/worms",
		"box": "1;1;1",
		"scale": "1;1;1",
		"rotation": "0;0;0",
		"origin_offset": "0.0;-0.5;0.0",
		"card": "assets/textures/cards/worms.png",
		"sound_drop": "assets/sounds/worms_drop.mp3",
		"sound_eat": "assets/sounds/worms_eat.mp3",
		"sound_pickup": "assets/sounds/worms_pickup.mp3",
	},
	{
		"name": "egg",
		"saturation": 0.01,
		"model": "assets/models/egg",
		"box": "0.641;0.518;0.540",
		"scale": "1;1;1",
		"rotation": "0;0;0",
		"origin_offset": "-0.090;0.001;-0.014",
		"card": "assets/textures/cards/egg.png",
		"sound_drop": "assets/sounds/egg_drop.mp3",
		"sound_eat": "assets/sounds/egg_eat.mp3",
		"sound_pickup": "assets/sounds/egg_pickup.mp3",
		"originoffset": "-0.090;0.001;-0.014",
	},
	{
		"name": "milk",
		"saturation": -0.03,
		"model": "assets/models/milk",
		"box": "0.533;1.027;0.401",
		"scale": "1;1;1",
		"rotation": "0;0;0",
		"origin_offset": "0.000;-0.089;0.000",
		"card": "assets/textures/cards/milk.png",
		"sound_drop": "assets/sounds/milk_drop.mp3",
		"sound_eat": "assets/sounds/milk_eat.mp3",
		"sound_pickup": "assets/sounds/milk_pickup.mp3",
		"originoffset": "0.000;-0.425;0.000",
	},
	{
		"name": "cockroach",
		"saturation": 0.05,
		"model": "assets/models/cockroach",
		"box": "1.156;0.559;1.283",
		"scale": "1;1;1",
		"rotation": "0;0;0",
		"origin_offset": "-0.095;-0.206;-0.125",
		"card": "assets/textures/cards/cockroach.png",
		"sound_drop": "assets/sounds/cockroach_drop.mp3",
		"sound_eat": "assets/sounds/cockroach_eat.mp3",
		"sound_pickup": "assets/sounds/cockroach_pickup.mp3",
		"originoffset": "-0.095;0.206;-0.125",
	},
	{
		"name": "nail",
		"saturation": 0.25,
		"model": "assets/models/nail",
		"box": "0.385;0.184;1.076",
		"scale": "1;1;1",
		"rotation": "0;0;0",
		"origin_offset": "0.015;-0.043;-0.051",
		"card": "assets/textures/cards/nail.png",
		"sound_drop": "assets/sounds/nail_drop.mp3",
		"sound_eat": "assets/sounds/nail_eat.mp3",
		"sound_pickup": "assets/sounds/nail_pickup.mp3",
		"originoffset": "0.015;0.043;-0.051",
	},
	{
		"name": "bloodbag",
		"saturation": 0.2,
		"model": "assets/models/bloodbag",
		"box": "1.083;0.467;1.302",
		"scale": "1;1;1",
		"rotation": "0;0;0",
		"origin_offset": "-0.012;-0.143;0.019",
		"card": "assets/textures/cards/bloodbag.png",
		"sound_drop": "assets/sounds/bloodbag_drop.mp3",
		"sound_eat": "assets/sounds/bloodbag_eat.mp3",
		"sound_pickup": "assets/sounds/bloodbag_pickup.mp3",
		"originoffset": "-0.012;0.033;0.019",
	},
	{
		"name": "cake",
		"saturation": 0.4,
		"model": "assets/models/cake",
		"box": "1.413;0.950;1.413",
		"scale": "1;1;1",
		"rotation": "0;0;0",
		"origin_offset": "-0.001;0.135;-0.000",
		"card": "assets/textures/cards/cake.png",
		"sound_drop": "assets/sounds/cake_drop.mp3",
		"sound_eat": "assets/sounds/cake_eat.mp3",
		"sound_pickup": "assets/sounds/cake_pickup.mp3",
		"originoffset": "-0.001;-0.085;-0.000",
	},
	{
		"name": "hair",
		"saturation": 0.7,
		"model": "assets/models/hair",
		"box": "0.6;0.3;0.3",
		"scale": "1;1;1",
		"rotation": "0;0;0",
		"origin_offset": "0.0;0;0.0",
		"card": "assets/textures/cards/hair.png",
		"sound_drop": "assets/sounds/default_drop.mp3",
		"sound_eat": "assets/sounds/noodles_eat.mp3",
		"sound_pickup": "assets/sounds/default_pickup.mp3"
	},
	{
		"name": "candy",
		"saturation": -0.3,
		"model": "assets/models/candy",
		"box": "0.5;0.3;0.3",
		"scale": "1;1;1",
		"rotation": "0;0;0",
		"origin_offset": "0.0;-0;0.0",
		"card": "assets/textures/cards/candy.png",
		"sound_drop": "assets/sounds/candy_drop.mp3",
		"sound_eat": "assets/sounds/candy_eat.mp3",
		"sound_pickup": "assets/sounds/candy_pickup.mp3"
	},
	{
		"name": "foil",
		"saturation": 0.0,
		"model": "assets/models/foil",
		"box": "0.5;0.5;0.5",
		"scale": "1;1;1",
		"rotation": "0;0;0",
		"origin_offset": "0.0;0;0.0",
		"card": "assets/textures/cards/foil.png",
		"sound_drop": "assets/sounds/foil_drop.mp3",
		"sound_eat": "assets/sounds/foil_eat.mp3",
		"sound_pickup": "assets/sounds/foil_pickup.mp3"
	},
	{
		"name": "gold",
		"saturation": 0.0,
		"model": "assets/models/gold",
		"box": "0.8;0.3;0.8",
		"scale": "1;1;1",
		"rotation": "0;0;0",
		"origin_offset": "0.0;0;0.0",
		"card": "assets/textures/cards/gold.png",
		"sound_drop": "assets/sounds/gold_drop.mp3",
		"sound_eat": "assets/sounds/gold_eat.mp3",
		"sound_pickup": "assets/sounds/gold_pickup.mp3"
	}
	],
	"pipe" :  {
		"objects" : [
			{"name": "egg", "percent": 0.35},
			{"name": "cockroach", "percent": 0.3},
			{"name": "milk", "percent": 0.35}
		]
	},
	"combinations": [
		{
			"from": [ "can" ],
			"timer_value": 0,
			"to": [
				{
					"object": "foil",
					"percent": 1.0
				}
			]
		},
		{
			"from": [ "foil" ],
			"timer_value": 0,
			"to": [
				{
					"object": "gold",
					"percent": 1.0
				}
			]
		},
		{
			"from": [ "worms", "fish" ],
			"timer_value": 1,
			"to": [
				{
					"object": "can",
					"percent": 1.0
				}
			]
		},
		{
			"from": [ "finger", "glass" ],
			"timer_value": 1,
			"to": [
				{
					"object": "worms",
					"percent": 1.0
				}
			]
		},
		{
			"from": [ "glass", "rat" ],
			"timer_value": 1,
			"to": [
				{
					"object": "fish",
					"percent": 1.0
				}
			]
		},
		{
			"from": [ "sausages", "ketchup" ],
			"timer_value": 1,
			"to": [
				{
					"object": "finger",
					"percent": 1.0
				}
			]
		},
		{
			"from": [ "egg", "cockroach" ],
			"timer_value": 1,
			"to": [
				{
					"object": "glass",
					"percent": 1.0
				}
			]
		},
		{
			"from": [ "blade", "cockroach" ],
			"timer_value": 1,
			"to": [
				{
					"object": "glass",
					"percent": 1.0
				}
			]
		},
		{
			"from": [ "brain", "skull" ],
			"timer_value": 1,
			"to": [
				{
					"object": "rat",
					"percent": 1.0
				}
			]
		},
		{
			"from": [ "milk", "cockroach" ],
			"timer_value": 1,
			"to": [
				{
					"object": "sausages",
					"percent": 1.0
				}
			]
		},
		{
			"from": [ "sausages", "nudlez" ],
			"timer_value": 1,
			"to": [
				{
					"object": "ketchup",
					"percent": 1.0
				}
			]
		},
		{
			"from": [ "apple" ],
			"timer_value": 0,
			"to": [
				{
					"object": "brain",
					"percent": 1.0
				}
			]
		},
		{
			"from": [ "tooth", "seeds" ],
			"timer_value": 1,
			"to": [
				{
					"object": "skull",
					"percent": 1.0
				}
			]
		},
		{
			"from": [ "egg", "milk" ],
			"timer_value": 1,
			"to": [
				{
					"object": "nudlez",
					"percent": 1.0
				}
			]
		},
		{
			"from": [ "milk" ],
			"timer_value": 0,
			"to": [
				{
					"object": "tooth",
					"percent": 1.0
				}
			]
		},
		{
			"from": [ "apple", "blade" ],
			"timer_value": 1,
			"to": [
				{
					"object": "seeds",
					"percent": 1.0
				}
			]
		},
		{
			"from": [ "nudlez" ],
			"timer_value": 0,
			"to": [
				{
					"object": "nail",
					"percent": 1.0
				}
			]
		},
		{
			"from": [ "nail" ],
			"timer_value": 0,
			"to": [
				{
					"object": "blade",
					"percent": 1.0
				}
			]
		},
		{
			"from": [ "egg" ],
			"timer_value": 0,
			"to": [
				{
					"object": "apple",
					"percent": 1.0
				}
			]
		},
		{
			"from": [ "seeds" ],
			"timer_value": 0,
			"to": [
				{
					"object": "apple",
					"percent": 1.0
				}
			]
		},
		{
			"from": [ "worms" ],
			"timer_value": 0,
			"to": [
				{
					"object": "hair",
					"percent": 1.0
				}
			]
		},
		{
			"from": [ "skull" ],
			"timer_value": 0,
			"to": [
				{
					"object": "mask",
					"percent": 1.0
				}
			]
		},
		{
			"from": [ "milk", "apple" ],
			"timer_value": 1,
			"to": [
				{
					"object": "cake",
					"percent": 1.0
				}
			]
		},
		{
			"from": [ "apple", "egg" ],
			"timer_value": 1,
			"to": [
				{
					"object": "cake",
					"percent": 1.0
				}
			]
		},
		{
			"from": [ "cockroach" ],
			"timer_value": 1,
			"to": [
				{
					"object": "cockroach",
					"percent": 1.0
				}
			]
		},
		{
			"from": [ "nudlez" ],
			"timer_value": 1,
			"to": [
				{
					"object": "hair",
					"percent": 1.0
				}
			]
		},
		{
			"from": [ "rat", "blade" ],
			"timer_value": 1,
			"to": [
				{
					"object": "bloodbag",
					"percent": 1.0
				}
			]
		},
		{
			"from": [ "fish", "blade" ],
			"timer_value": 1,
			"to": [
				{
					"object": "bloodbag",
					"percent": 1.0
				}
			]
		},
		{
			"from": [ "ketchup" ],
			"timer_value": 0,
			"to": [
				{
					"object": "bloodbag",
					"percent": 1.0
				}
			]
		},
		{
			"from": [ "nudlez", "blade" ],
			"timer_value": 1,
			"to": [
				{
					"object": "hair",
					"percent": 1.0
				}
			]
		},
		{
			"from": [ "apple", "tooth" ],
			"timer_value": 1,
			"to": [
				{
					"object": "seeds",
					"percent": 1.0
				}
			]
		},
		{
			"from": [ "apple", "nail" ],
			"timer_value": 1,
			"to": [
				{
					"object": "seeds",
					"percent": 1.0
				}
			]
		},
		{
			"from": [ "milk", "tooth" ],
			"timer_value": 1,
			"to": [
				{
					"object": "candy",
					"percent": 1.0
				}
			]
		}
	]
}
